[
  {
    "name": "SG Antiques Jewellery",
    "logo": "SG",
    "tagline": "Jewellery Manufacturers",
    "phone": "9865031824, 0422-2341991",
    "email": "anticjewels.cbe@gmail.com",
    "addr": "22B, Raj Nagar, Selvapuram, Coimbatore - 641026",
    "gstin": "33DUSPS7454F1Z0",
    "bank": "Axis Bank, Town Hall",
    "acc": "918020021078772",
    "ifsc": "UTIB0001919"
  },
  {
    "name": "Loki",
    "logo": "LG",
    "tagline": "",
    "phone": "r454r54545",
    "email": "454554545",
    "addr": "",
    "gstin": "",
    "bank": "",
    "acc": "",
    "ifsc": ""
  },
  {
    "name": "new",
    "logo": "",
    "tagline": "",
    "phone": "",
    "email": "",
    "addr": "",
    "gstin": "",
    "bank": "",
    "acc": "",
    "ifsc": ""
  },
  {
    "name": "Rishvik Jewellery",
    "logo": "R*L",
    "tagline": "Jewellery Makers",
    "phone": "9894058144",
    "email": "logesh.appusamy@gmail.com",
    "addr": "Selvapuram, Coimbatore",
    "gstin": "",
    "bank": "",
    "acc": "",
    "ifsc": ""
  },
  {
    "name": "TVK Jewellery",
    "logo": "TVK",
    "tagline": "jewellery",
    "phone": "1111111111111111111",
    "email": "5555555555555555",
    "addr": "5555555555555555",
    "gstin": "",
    "bank": "",
    "acc": "",
    "ifsc": ""
  }
]